fastkde-2.1.5.dist-info/RECORD
fastkde-2.1.5.dist-info/WHEEL
fastkde-2.1.5.dist-info/top_level.txt
fastkde-2.1.5.dist-info/METADATA
fastkde-2.1.5.dist-info/licenses/LICENSE.txt
fastkde/empiricalCharacteristicFunction.py
fastkde/plot.py
fastkde/nufft.pyx
fastkde/nufft.cpython-310-darwin.so
fastkde/nufft.c
fastkde/__init__.py
fastkde/floodFillSearch.cpython-310-darwin.so
fastkde/convergence_tests.py
fastkde/fastKDE.py
fastkde/floodFillSearch.c
fastkde/floodFillSearch.pyx
