Metadata-Version: 2.4
Name: fastkde
Version: 2.1.5
Summary: Tools for fast and robust univariate and multivariate kernel density estimation
Home-page: https://github.com/LBL-EESA/fastkde
Download-URL: https://github.com/LBL-EESA/fastkde/archive/v2.1.5.tar.gz
Author: Travis A. O'Brien
Author-email: obrienta@iu.edu
Keywords: statistics,probability,KDE,kernel density estimation
Requires-Python: >=3.9
License-File: LICENSE.txt
Requires-Dist: numpy>=1.26.4
Requires-Dist: scipy
Requires-Dist: xarray
Provides-Extra: test
Requires-Dist: pytest; extra == "test"
Provides-Extra: dev
Requires-Dist: pytest; extra == "dev"
Provides-Extra: all
Requires-Dist: pytest; extra == "all"
Dynamic: author
Dynamic: author-email
Dynamic: description
Dynamic: description-content-type
Dynamic: download-url
Dynamic: home-page
Dynamic: keywords
Dynamic: license-file
Dynamic: provides-extra
Dynamic: summary
